{
  "filename": "EndlessLedgeChests.dat",
  "header": [
    {
      "name": "Id",
      "rowid": 0,
      "type": "ref|string",
      "key": null,
      "key_id": null,
      "key_offset": 0,
      "enum": null,
      "unique": true,
      "file_path": false,
      "file_ext": null,
      "display": null,
      "display_type": "{0}",
      "description": null
    },
    {
      "name": "WorldAreasKey",
      "rowid": 1,
      "type": "ulong",
      "key": "WorldAreas.dat",
      "key_id": null,
      "key_offset": 0,
      "enum": null,
      "unique": false,
      "file_path": false,
      "file_ext": null,
      "display": null,
      "display_type": "{0}",
      "description": null
    },
    {
      "name": "BaseItemTypesKeys",
      "rowid": 2,
      "type": "ref|list|ulong",
      "key": "BaseItemTypes.dat",
      "key_id": null,
      "key_offset": 0,
      "enum": null,
      "unique": false,
      "file_path": false,
      "file_ext": null,
      "display": null,
      "display_type": "{0}",
      "description": null
    },
    {
      "name": "SocketColour",
      "rowid": 3,
      "type": "ref|string",
      "key": null,
      "key_id": null,
      "key_offset": 0,
      "enum": null,
      "unique": false,
      "file_path": false,
      "file_ext": null,
      "display": null,
      "display_type": "{0}",
      "description": null
    }
  ],
  "data": [
    [
      "ProxyKey1",
      1346,
      [
        3588
      ],
      "R_G_B"
    ],
    [
      "ProxyKey2",
      1346,
      [
        3694
      ],
      "R_G_B"
    ],
    [
      "ProxyKey3",
      1346,
      [
        3367
      ],
      "R_G_B"
    ],
    [
      "ProxyKey4",
      1346,
      [
        3846
      ],
      "R_G_B"
    ],
    [
      "ProxyKey5",
      1346,
      [
        3807
      ],
      "R_G_B"
    ],
    [
      "ProxyKey6",
      1346,
      [
        3560
      ],
      "R_G_B"
    ],
    [
      "ProxyKey7",
      1346,
      [
        3532
      ],
      "R_G_B"
    ],
    [
      "ProxyKey8",
      1346,
      [
        3479
      ],
      "R_G_B"
    ],
    [
      "ProxyKey9",
      1346,
      [
        3390
      ],
      "R_G_B"
    ],
    [
      "ProxyKey28",
      1346,
      [
        4228
      ],
      ""
    ],
    [
      "ProxyKey29",
      1346,
      [
        4251
      ],
      ""
    ],
    [
      "ProxyKey30",
      1346,
      [
        3905
      ],
      "R_G_B"
    ],
    [
      "ProxyKey31",
      1346,
      [
        1
      ],
      ""
    ],
    [
      "ProxyKey32",
      1346,
      [
        1
      ],
      ""
    ],
    [
      "ProxyKey33",
      1346,
      [
        1
      ],
      ""
    ],
    [
      "ProxyKey34",
      1346,
      [
        1
      ],
      ""
    ],
    [
      "ProxyKey35",
      1346,
      [
        1
      ],
      ""
    ],
    [
      "ProxyKey10",
      1346,
      [
        4424
      ],
      ""
    ],
    [
      "ProxyKey11",
      1346,
      [
        4431
      ],
      ""
    ],
    [
      "ProxyKey12",
      1346,
      [
        4432
      ],
      ""
    ],
    [
      "ProxyKey13",
      1346,
      [
        4435
      ],
      ""
    ],
    [
      "ProxyKey14",
      1346,
      [
        4439
      ],
      ""
    ],
    [
      "ProxyKey15",
      1346,
      [
        4443
      ],
      ""
    ],
    [
      "ProxyKey16",
      1346,
      [
        4450
      ],
      ""
    ],
    [
      "ProxyKey17",
      1346,
      [
        4452
      ],
      ""
    ],
    [
      "ProxyKey18",
      1346,
      [
        4488
      ],
      ""
    ],
    [
      "ProxyKey19",
      1346,
      [
        4490
      ],
      ""
    ],
    [
      "ProxyKey20",
      1346,
      [
        4493
      ],
      ""
    ],
    [
      "ProxyKey21",
      1346,
      [
        4516
      ],
      ""
    ],
    [
      "ProxyKey22",
      1346,
      [
        4547
      ],
      ""
    ],
    [
      "ProxyKey23",
      1346,
      [
        4565
      ],
      ""
    ],
    [
      "ProxyKey24",
      1346,
      [
        4568
      ],
      ""
    ],
    [
      "ProxyKey25",
      1346,
      [
        4604
      ],
      ""
    ],
    [
      "ProxyKey26",
      1346,
      [
        4658
      ],
      ""
    ],
    [
      "ProxyKey27",
      1346,
      [
        4680
      ],
      ""
    ],
    [
      "ProxyKey36",
      1346,
      [
        4700
      ],
      ""
    ],
    [
      "ProxyKey37",
      1346,
      [
        4706
      ],
      ""
    ],
    [
      "ProxyKey38",
      1346,
      [
        4710
      ],
      ""
    ]
  ]
}