{
  "filename": "HarvestPlantBoosters.dat",
  "header": [
    {
      "name": "HarvestObjectsKey",
      "rowid": 0,
      "type": "ulong",
      "key": "HarvestObjects.dat",
      "key_id": null,
      "key_offset": 0,
      "enum": null,
      "unique": true,
      "file_path": false,
      "file_ext": null,
      "display": null,
      "display_type": "{0}",
      "description": null
    },
    {
      "name": "Radius",
      "rowid": 1,
      "type": "int",
      "key": null,
      "key_id": null,
      "key_offset": 0,
      "enum": null,
      "unique": false,
      "file_path": false,
      "file_ext": null,
      "display": null,
      "display_type": "{0}",
      "description": null
    },
    {
      "name": "Key0",
      "rowid": 2,
      "type": "ulong",
      "key": null,
      "key_id": null,
      "key_offset": 0,
      "enum": null,
      "unique": false,
      "file_path": false,
      "file_ext": null,
      "display": null,
      "display_type": "{0}",
      "description": null
    },
    {
      "name": "Lifeforce",
      "rowid": 3,
      "type": "int",
      "key": null,
      "key_id": null,
      "key_offset": 0,
      "enum": null,
      "unique": false,
      "file_path": false,
      "file_ext": null,
      "display": null,
      "display_type": "{0}",
      "description": null
    },
    {
      "name": "AdditionalCraftingOptionsChance",
      "rowid": 4,
      "type": "int",
      "key": null,
      "key_id": null,
      "key_offset": 0,
      "enum": null,
      "unique": false,
      "file_path": false,
      "file_ext": null,
      "display": null,
      "display_type": "{0}",
      "description": null
    },
    {
      "name": "RareExtraChances",
      "rowid": 5,
      "type": "int",
      "key": null,
      "key_id": null,
      "key_offset": 0,
      "enum": null,
      "unique": false,
      "file_path": false,
      "file_ext": null,
      "display": null,
      "display_type": "{0}",
      "description": null
    },
    {
      "name": "HarvestPlantBoosterFamilies",
      "rowid": 6,
      "type": "int",
      "key": null,
      "key_id": null,
      "key_offset": 0,
      "enum": null,
      "unique": false,
      "file_path": false,
      "file_ext": null,
      "display": null,
      "display_type": "{0}",
      "description": null
    }
  ],
  "data": [
    [
      55,
      5,
      403,
      0,
      0,
      1,
      1
    ],
    [
      56,
      5,
      403,
      0,
      0,
      2,
      1
    ],
    [
      57,
      5,
      403,
      0,
      0,
      3,
      1
    ],
    [
      58,
      5,
      403,
      100,
      0,
      0,
      0
    ],
    [
      59,
      5,
      403,
      150,
      0,
      0,
      0
    ],
    [
      60,
      5,
      403,
      200,
      0,
      0,
      0
    ],
    [
      61,
      5,
      403,
      0,
      20,
      0,
      2
    ],
    [
      62,
      5,
      403,
      0,
      30,
      0,
      2
    ],
    [
      63,
      5,
      403,
      0,
      40,
      0,
      2
    ]
  ]
}