{
  "filename": "PassiveTreeExpansionSpecialSkills.dat",
  "header": [
    {
      "name": "PassiveSkillsKey",
      "rowid": 0,
      "type": "ulong",
      "key": "PassiveSkills.dat",
      "key_id": null,
      "key_offset": 0,
      "enum": null,
      "unique": false,
      "file_path": false,
      "file_ext": null,
      "display": null,
      "display_type": "{0}",
      "description": null
    },
    {
      "name": "StatsKey",
      "rowid": 1,
      "type": "ulong",
      "key": "Stats.dat",
      "key_id": null,
      "key_offset": 0,
      "enum": null,
      "unique": false,
      "file_path": false,
      "file_ext": null,
      "display": null,
      "display_type": "{0}",
      "description": null
    }
  ],
  "data": [
    [
      2552,
      10985
    ],
    [
      2553,
      11481
    ],
    [
      2554,
      11482
    ],
    [
      2555,
      11483
    ],
    [
      2556,
      11484
    ],
    [
      2557,
      11486
    ],
    [
      2558,
      11487
    ],
    [
      2559,
      11485
    ],
    [
      2560,
      11178
    ],
    [
      2561,
      11179
    ],
    [
      2562,
      11180
    ],
    [
      2563,
      11181
    ],
    [
      2564,
      11182
    ],
    [
      2565,
      11183
    ],
    [
      2566,
      11184
    ],
    [
      2567,
      11185
    ],
    [
      2568,
      11186
    ],
    [
      2569,
      11187
    ],
    [
      2570,
      11188
    ],
    [
      2571,
      11189
    ],
    [
      2572,
      11190
    ],
    [
      2573,
      11191
    ],
    [
      2574,
      11192
    ],
    [
      2575,
      11193
    ],
    [
      2576,
      11194
    ],
    [
      2577,
      11195
    ],
    [
      2578,
      11196
    ],
    [
      2579,
      11197
    ],
    [
      2580,
      11198
    ],
    [
      2581,
      11199
    ],
    [
      2582,
      11200
    ],
    [
      2583,
      11201
    ],
    [
      2584,
      11202
    ],
    [
      2588,
      11203
    ],
    [
      2589,
      11204
    ],
    [
      2590,
      11205
    ],
    [
      2591,
      11206
    ],
    [
      2592,
      11207
    ],
    [
      2593,
      11208
    ],
    [
      2594,
      11209
    ],
    [
      2595,
      11210
    ],
    [
      2596,
      11211
    ],
    [
      2597,
      11212
    ],
    [
      2598,
      11213
    ],
    [
      2599,
      11214
    ],
    [
      2600,
      11215
    ],
    [
      2601,
      11216
    ],
    [
      2602,
      11217
    ],
    [
      2603,
      11218
    ],
    [
      2604,
      11219
    ],
    [
      2605,
      11220
    ],
    [
      2606,
      11221
    ],
    [
      2607,
      11222
    ],
    [
      2608,
      11223
    ],
    [
      2609,
      11224
    ],
    [
      2610,
      11225
    ],
    [
      2611,
      11226
    ],
    [
      2612,
      11227
    ],
    [
      2613,
      11228
    ],
    [
      2614,
      11229
    ],
    [
      2615,
      11230
    ],
    [
      2616,
      11231
    ],
    [
      2617,
      11232
    ],
    [
      2618,
      11233
    ],
    [
      2619,
      11234
    ],
    [
      2620,
      11235
    ],
    [
      2621,
      11236
    ],
    [
      2622,
      11237
    ],
    [
      2623,
      11238
    ],
    [
      2624,
      11239
    ],
    [
      2625,
      11240
    ],
    [
      2626,
      11241
    ],
    [
      2627,
      11242
    ],
    [
      2628,
      11243
    ],
    [
      2629,
      11244
    ],
    [
      2630,
      11245
    ],
    [
      2631,
      11246
    ],
    [
      2632,
      11247
    ],
    [
      2633,
      11248
    ],
    [
      2634,
      11249
    ],
    [
      2635,
      11250
    ],
    [
      2636,
      11251
    ],
    [
      2637,
      11252
    ],
    [
      2638,
      11253
    ],
    [
      2639,
      11254
    ],
    [
      2640,
      11255
    ],
    [
      2641,
      11256
    ],
    [
      2642,
      11257
    ],
    [
      2643,
      11258
    ],
    [
      2644,
      11259
    ],
    [
      2645,
      11260
    ],
    [
      2646,
      11261
    ],
    [
      2647,
      11262
    ],
    [
      2648,
      11263
    ],
    [
      2649,
      11264
    ],
    [
      2650,
      11265
    ],
    [
      2651,
      11266
    ],
    [
      2652,
      11267
    ],
    [
      2653,
      11268
    ],
    [
      2654,
      11269
    ],
    [
      2655,
      11270
    ],
    [
      2656,
      11271
    ],
    [
      2657,
      11272
    ],
    [
      2658,
      11273
    ],
    [
      2659,
      11274
    ],
    [
      2660,
      11275
    ],
    [
      2661,
      11276
    ],
    [
      2662,
      11277
    ],
    [
      2663,
      11278
    ],
    [
      2664,
      11279
    ],
    [
      2665,
      11280
    ],
    [
      2666,
      11281
    ],
    [
      2667,
      11282
    ],
    [
      2668,
      11283
    ],
    [
      2669,
      11284
    ],
    [
      2670,
      11285
    ],
    [
      2671,
      11286
    ],
    [
      2672,
      11287
    ],
    [
      2673,
      11288
    ],
    [
      2674,
      11289
    ],
    [
      2675,
      11290
    ],
    [
      2676,
      11291
    ],
    [
      2677,
      11292
    ],
    [
      2678,
      11293
    ],
    [
      2679,
      11294
    ],
    [
      2680,
      11295
    ],
    [
      2681,
      11296
    ],
    [
      2682,
      11297
    ],
    [
      2683,
      11298
    ],
    [
      2684,
      11299
    ],
    [
      2685,
      11300
    ],
    [
      2686,
      11301
    ],
    [
      2687,
      11302
    ],
    [
      2688,
      11303
    ],
    [
      2689,
      11304
    ],
    [
      2690,
      11305
    ],
    [
      2691,
      11306
    ],
    [
      2692,
      11307
    ],
    [
      2693,
      11308
    ],
    [
      2694,
      11309
    ],
    [
      2695,
      11310
    ],
    [
      2696,
      11311
    ],
    [
      2697,
      11312
    ],
    [
      2698,
      11313
    ],
    [
      2699,
      11314
    ],
    [
      2700,
      11315
    ],
    [
      2701,
      11604
    ],
    [
      2702,
      11316
    ],
    [
      2703,
      11317
    ],
    [
      2704,
      11318
    ],
    [
      2705,
      11319
    ],
    [
      2706,
      11320
    ],
    [
      2707,
      11321
    ],
    [
      2708,
      11322
    ],
    [
      2709,
      11323
    ],
    [
      2710,
      11324
    ],
    [
      2711,
      11325
    ],
    [
      2712,
      11326
    ],
    [
      2713,
      11327
    ],
    [
      2714,
      11328
    ],
    [
      2715,
      11329
    ],
    [
      2716,
      11330
    ],
    [
      2717,
      11331
    ],
    [
      2718,
      11332
    ],
    [
      2719,
      11333
    ],
    [
      2720,
      11334
    ],
    [
      2721,
      11335
    ],
    [
      2722,
      11336
    ],
    [
      2723,
      11337
    ],
    [
      2724,
      11338
    ],
    [
      2725,
      11339
    ],
    [
      2726,
      11340
    ],
    [
      2727,
      11341
    ],
    [
      2728,
      11342
    ],
    [
      2729,
      11343
    ],
    [
      2730,
      11344
    ],
    [
      2731,
      11345
    ],
    [
      2732,
      11346
    ],
    [
      2733,
      11347
    ],
    [
      2734,
      11348
    ],
    [
      2735,
      11349
    ],
    [
      2736,
      11350
    ],
    [
      2737,
      11351
    ],
    [
      2738,
      11352
    ],
    [
      2739,
      11353
    ],
    [
      2740,
      11354
    ],
    [
      2741,
      11355
    ],
    [
      2742,
      11356
    ],
    [
      2748,
      11357
    ],
    [
      2749,
      11358
    ],
    [
      2750,
      11359
    ],
    [
      2751,
      11360
    ],
    [
      2752,
      11361
    ],
    [
      2753,
      11362
    ],
    [
      2754,
      11363
    ],
    [
      2755,
      11364
    ],
    [
      2756,
      11365
    ],
    [
      2757,
      11366
    ],
    [
      2758,
      11367
    ],
    [
      2759,
      11368
    ],
    [
      2760,
      11369
    ],
    [
      2761,
      11370
    ],
    [
      2762,
      11371
    ],
    [
      2763,
      11372
    ],
    [
      2764,
      11373
    ],
    [
      2765,
      11374
    ],
    [
      2766,
      11375
    ],
    [
      2767,
      11376
    ],
    [
      2768,
      11377
    ],
    [
      2769,
      11378
    ],
    [
      2770,
      11379
    ],
    [
      2771,
      11380
    ],
    [
      2772,
      11381
    ],
    [
      2773,
      11382
    ],
    [
      2774,
      11383
    ],
    [
      2775,
      11384
    ],
    [
      2776,
      11385
    ],
    [
      2777,
      11386
    ],
    [
      2778,
      11387
    ],
    [
      2779,
      11388
    ],
    [
      2780,
      11389
    ],
    [
      2781,
      11390
    ],
    [
      2782,
      11391
    ],
    [
      2783,
      11392
    ],
    [
      2784,
      11393
    ],
    [
      2785,
      11394
    ],
    [
      2786,
      11395
    ],
    [
      2787,
      11396
    ],
    [
      2788,
      11397
    ],
    [
      2789,
      11398
    ],
    [
      2790,
      11399
    ],
    [
      2791,
      11400
    ],
    [
      2792,
      11401
    ],
    [
      2793,
      11402
    ],
    [
      2794,
      11403
    ],
    [
      2795,
      11404
    ],
    [
      2796,
      11405
    ],
    [
      2797,
      11406
    ],
    [
      2798,
      11407
    ],
    [
      2799,
      11408
    ],
    [
      2800,
      11409
    ],
    [
      2801,
      11410
    ],
    [
      2802,
      11411
    ],
    [
      2803,
      11412
    ],
    [
      2804,
      11413
    ],
    [
      2805,
      11414
    ],
    [
      2807,
      11415
    ],
    [
      2808,
      11416
    ],
    [
      2809,
      11417
    ],
    [
      2810,
      11418
    ],
    [
      2811,
      11419
    ],
    [
      2812,
      11420
    ],
    [
      2814,
      11421
    ],
    [
      2815,
      11422
    ],
    [
      2816,
      11423
    ],
    [
      2817,
      11424
    ],
    [
      2818,
      11425
    ],
    [
      2820,
      11426
    ],
    [
      2821,
      11427
    ],
    [
      2822,
      11428
    ],
    [
      2823,
      11429
    ],
    [
      2824,
      11430
    ],
    [
      2825,
      11431
    ],
    [
      2826,
      11432
    ],
    [
      2827,
      11433
    ],
    [
      2828,
      11434
    ],
    [
      2829,
      11435
    ],
    [
      2830,
      11436
    ],
    [
      2831,
      11437
    ],
    [
      2832,
      11438
    ],
    [
      2833,
      11439
    ],
    [
      2834,
      11440
    ],
    [
      2835,
      11441
    ],
    [
      2836,
      11442
    ],
    [
      2837,
      11443
    ],
    [
      2838,
      11444
    ],
    [
      2839,
      11445
    ],
    [
      2840,
      11446
    ],
    [
      2841,
      11447
    ],
    [
      2842,
      11448
    ],
    [
      2843,
      11449
    ],
    [
      2844,
      11450
    ],
    [
      2845,
      11451
    ],
    [
      2846,
      11452
    ],
    [
      2847,
      11453
    ],
    [
      2848,
      11454
    ],
    [
      2849,
      11455
    ],
    [
      2850,
      11456
    ],
    [
      2851,
      11457
    ],
    [
      2743,
      12302
    ],
    [
      2744,
      12303
    ],
    [
      2745,
      12304
    ],
    [
      2746,
      12305
    ],
    [
      2747,
      12306
    ],
    [
      2806,
      12307
    ],
    [
      2813,
      12308
    ],
    [
      2819,
      12309
    ],
    [
      2585,
      12365
    ],
    [
      2586,
      12366
    ],
    [
      2587,
      12367
    ]
  ]
}